duvals_triangle_plotter/__init__.py
duvals_triangle_plotter/__main__.py
duvals_triangle_plotter/constants.py
duvals_triangle_plotter/duvals_triangle_plotter.py
duvals_triangle_plotter-1.0.dist-info/LICENSE.txt
duvals_triangle_plotter-1.0.dist-info/METADATA
duvals_triangle_plotter-1.0.dist-info/WHEEL
duvals_triangle_plotter-1.0.dist-info/entry_points.txt
duvals_triangle_plotter-1.0.dist-info/top_level.txt
duvals_triangle_plotter-1.0.dist-info/RECORD
