Metadata-Version: 2.1
Name: duvals-triangle-plotter
Version: 1.0
Summary: Duval's Triangle Plotter - Python library for generating Duval's Triangle plots
Home-page: https://github.com/yourusername/duvals_triangle_plotter
Author: Subramanian Narayanan
Author-email: your.email@example.com
License: MIT
Classifier: License :: OSI Approved :: MIT License
Classifier: Programming Language :: Python :: 3
Classifier: Programming Language :: Python :: 3.6
Classifier: Programming Language :: Python :: 3.7
Classifier: Programming Language :: Python :: 3.8
Classifier: Programming Language :: Python :: 3.9
License-File: LICENSE.txt
Requires-Dist: plotly
